<?xml version="1.0" encoding="UTF-8"?>
<Employees>
    <Employee>
        <ID>1</ID>
        <FirstName>Alice</FirstName>
        <LastName>Johnson</LastName>
        <Department>HR</Department>
        <Email>alice.johnson@company.com</Email>
    </Employee>

    <Employee>
        <ID>2</ID>
        <FirstName>Bob</FirstName>
        <LastName>Smith</LastName>
        <Department>IT</Department>
        <Email>bob.smith@company.com</Email>
    </Employee>

    <Employee>
        <ID>3</ID>
        <FirstName>Charlie</FirstName>
        <LastName>Brown</LastName>
        <Department>Finance</Department>
        <Email>charlie.brown@company.com</Email>
    </Employee>
</Employees>
